LICENSE
MANIFEST.in
README.md
setup.py
Captcha_Net/__init__.py
Captcha_Net.egg-info/PKG-INFO
Captcha_Net.egg-info/SOURCES.txt
Captcha_Net.egg-info/dependency_links.txt
Captcha_Net.egg-info/requires.txt
Captcha_Net.egg-info/top_level.txt
Captcha_Net/CNN/CnnNetModule.py
Captcha_Net/CNN/__init__.py
Captcha_Net/CenterNet/CenterNetModule.py
Captcha_Net/CenterNet/__init__.py
Captcha_Net/CenterNet/voc_label.py
mypackage/__init__.py
mypackage/__version__.py
mypackage/core.py