Metadata-Version: 2.1
Name: Captcha-Net
Version: 0.2.3
Summary: About to learn Captcha_Net tools.
Home-page: https://github.com/me/myproject
Author: some one
Author-email: 546162357@qq.com
License: MIT
Platform: UNKNOWN
Classifier: License :: OSI Approved :: MIT License
Classifier: Programming Language :: Python
Classifier: Programming Language :: Python :: 3
Classifier: Programming Language :: Python :: 3.6
Classifier: Programming Language :: Python :: Implementation :: CPython
Classifier: Programming Language :: Python :: Implementation :: PyPy
Requires-Python: >=3.6.0
